azauthlib/__init__.py
azauthlib/_configure.py
azauthlib/_def.py
azauthlib/appdata.py
azauthlib/authentication.py
azauthlib/config_app.py
azauthlib/gui_utils.py
azauthlib/permissions.py
azauthlib/tokens.py
azauthlib/assets/gui_main.png
azauthlib-1.0.2b1.dist-info/METADATA
azauthlib-1.0.2b1.dist-info/WHEEL
azauthlib-1.0.2b1.dist-info/entry_points.txt
azauthlib-1.0.2b1.dist-info/top_level.txt
azauthlib-1.0.2b1.dist-info/RECORD
