Metadata-Version: 2.1
Name: azauthlib
Version: 1.0.2b1
Summary: A Python library simplifying Azure Microsoft Graph authentication. Provides an intuitive interface for acquiring access tokens through interactive login, silent authentication, device code flow, and client credentials flow. Includes utilities for seamless token storage and refresh management.
Home-page: https://github.com/cedricmoorejr/azauthlib/tree/v1.0.2b1
Author: Cedric Moore Jr.
Author-email: cedricmoorejunior5@gmail.com
License: Apache Software License
Project-URL: Source Code, https://github.com/cedricmoorejr/azauthlib/releases/tag/v1.0.2-beta.1
Classifier: Programming Language :: Python :: 3
Classifier: License :: OSI Approved :: Apache Software License
Classifier: Operating System :: Microsoft :: Windows
Classifier: Operating System :: POSIX :: Linux
Classifier: Operating System :: MacOS :: MacOS X
Classifier: Development Status :: 4 - Beta
Classifier: Intended Audience :: Developers
Classifier: Natural Language :: English
Classifier: Programming Language :: Python :: 3.8
Classifier: Programming Language :: Python :: 3.9
Classifier: Programming Language :: Python :: 3.10
Requires-Python: >=3.7
Requires-Dist: python-dotenv
Requires-Dist: portalocker
Requires-Dist: msal
